ondopy/__init__.py
ondopy/tr7nw.py
ondopy-0.2.1.dist-info/DESCRIPTION.rst
ondopy-0.2.1.dist-info/METADATA
ondopy-0.2.1.dist-info/RECORD
ondopy-0.2.1.dist-info/WHEEL
ondopy-0.2.1.dist-info/metadata.json
ondopy-0.2.1.dist-info/top_level.txt
