Metadata-Version: 2.0
Name: ondopy
Version: 0.2.1
Summary: driver for ondotori
Home-page: https://github.com/ars096/ondopy
Author: Atsushi Nishimura
Author-email: ars096@gmail.com
License: MIT
Platform: UNKNOWN
